{"schema":2,"brand":"Volkswagen All","source":"OBDb/Volkswagen","protocol":"6","pids":[{"cmd":"222A0C","hdr":"710","name":"SOC","unit":"%","target":"hv_soc","bix":0,"len":8,"mul":1,"add":0,"min":0,"max":100,"every":1,"src":"VOLKSWAGEN_SSB_SOC","rax":"77A"},{"cmd":"22202F","hdr":"714","name":"OIL","unit":"°C","target":"oil_temp","bix":0,"len":8,"mul":1,"add":-58,"min":-40,"max":255,"every":1,"src":"VOLKSWAGEN_EOT"},{"cmd":"221057","hdr":"7E0","name":"BOOST","unit":"bar","target":"boost","bix":0,"len":16,"mul":0.001,"add":0,"min":-1,"max":65.535,"every":4,"src":"VOLKSWAGEN_PQ35_CHG_P","rax":"7E8"},{"cmd":"222104","hdr":"7E1","name":"TRANS","unit":"°C","target":"trans_temp","bix":0,"len":8,"mul":1,"add":-40,"min":-40,"max":215,"every":4,"src":"VOLKSWAGEN_ATF_T","rax":"7E9"},{"cmd":"221E0E","hdr":"7E5","name":"HV TEMP","unit":"°C","target":"hv_temp","bix":0,"len":8,"mul":1,"add":-100,"min":-100,"max":155,"every":4,"src":"VOLKSWAGEN_BMS_T_MAX","rax":"7ED"}]}